flattools/pp.py
flattools/bin/__init__.py
flattools/bin/flatc.py
flattools/fbs/__init__.py
flattools/fbs/_compat.py
flattools/fbs/fbs.py
flattools/fbs/parser/__init__.py
flattools/fbs/parser/exc.py
flattools/fbs/parser/lexer.py
flattools/fbs/parser/parser.py
flattools/fbs/parser/parsetab.py
flattools/templates/__init__.py
flattools/templates/fbs_template.kt.j2
flattools/templates/fbs_template.py.j2
flattools/templates/fbs_template.rs.j2
flattools/templates/fbs_template.swift.j2
flattools/templates/fbs_template_cpp.h.j2
flattools/templates/fbs_template_interface.java.j2
flattools/templates/fbs_template_yaml.yaml.j2
flattools-0.6.2.dist-info/licenses/LICENSE
lang/__init__.py
lang/common.py
lang/cpp/__init__.py
lang/cpp/generate.py
lang/cpp/types.py
lang/java/__init__.py
lang/java/generate.py
lang/java/types.py
lang/kt/__init__.py
lang/kt/generate.py
lang/kt/types.py
lang/py/__init__.py
lang/py/generate.py
lang/py/types.py
lang/rust/__init__.py
lang/rust/generate.py
lang/rust/types.py
lang/swift/__init__.py
lang/swift/generate.py
lang/swift/types.py
lang/yaml/__init__.py
lang/yaml/generate.py
tests/expected/golden-color.py
flattools-0.6.2.dist-info/METADATA
flattools-0.6.2.dist-info/WHEEL
flattools-0.6.2.dist-info/entry_points.txt
flattools-0.6.2.dist-info/top_level.txt
flattools-0.6.2.dist-info/RECORD
