Metadata-Version: 2.4
Name: flattools
Version: 0.6.2
Summary: Pure Python Flatbuffer Schema Compiler
Author-email: Arun Sharma <asharma@fb.com>
License: MIT
Project-URL: Homepage, https://github.com/adsharma/flattools
Keywords: flatbuffers,python,thriftpy
Classifier: Topic :: Software Development
Classifier: Development Status :: 4 - Beta
Classifier: Intended Audience :: Developers
Classifier: License :: OSI Approved :: MIT License
Classifier: Programming Language :: Python :: 3
Classifier: Programming Language :: Python :: 3.6
Classifier: Programming Language :: Python :: 3.7
Classifier: Programming Language :: Python :: 3.8
Classifier: Programming Language :: Python :: 3.9
Classifier: Programming Language :: Python :: 3.10
Classifier: Programming Language :: Python :: 3.11
Classifier: Programming Language :: Python :: Implementation :: CPython
Classifier: Programming Language :: Python :: Implementation :: PyPy
Requires-Python: >=3.6
License-File: LICENSE
Requires-Dist: ply<4.0,>=3.4
Provides-Extra: dev
Requires-Dist: flake8>=2.5; extra == "dev"
Requires-Dist: pytest>=2.8; extra == "dev"
Requires-Dist: jinja2>=2.11; extra == "dev"
Dynamic: license-file
